trainplotkit/__init__.py
trainplotkit/layout.py
trainplotkit/plotgrid.py
trainplotkit/sanity_check.py
trainplotkit/utils.py
trainplotkit/subplots/activations.py
trainplotkit/subplots/basic.py
trainplotkit-0.2.0.dist-info/licenses/LICENSE
trainplotkit-0.2.0.dist-info/METADATA
trainplotkit-0.2.0.dist-info/WHEEL
trainplotkit-0.2.0.dist-info/top_level.txt
trainplotkit-0.2.0.dist-info/RECORD
