Metadata-Version: 2.4
Name: trainplotkit
Version: 0.2.0
Summary: Create live subplots in your notebook that update while training a PyTorch model
Author-email: Dirk Oosthuizen <dirk.jj.oosthuizen@gmail.com>
License: MIT
Project-URL: Repository, https://github.com/d112358/trainplotkit.git
Project-URL: Bug Tracker, https://github.com/d112358/trainplotkit/issues
Keywords: pytorch,torch,deep learning,neural network,training,visualization,interactive,dashboard,jupyter,notebook,plotly
Classifier: License :: OSI Approved :: MIT License
Classifier: Programming Language :: Python
Requires-Python: >=3.9
License-File: LICENSE
Requires-Dist: torch>=2.3.0
Requires-Dist: matplotlib
Requires-Dist: numpy
Requires-Dist: torcheval
Requires-Dist: plotly
Requires-Dist: nbformat
Requires-Dist: ipywidgets
Dynamic: license-file
